examples/multiprocessing_server.py
examples/server.py
mkfst/__init__.py
mkfst/auth/__init__.py
mkfst/auth/oauth2_authenticator.py
mkfst/auth/oidc_authenticator.py
mkfst/auth/saml_authenticator.py
mkfst/auth/jose/__init__.py
mkfst/auth/jose/constants.py
mkfst/auth/jose/exceptions.py
mkfst/auth/jose/jwe.py
mkfst/auth/jose/jwk.py
mkfst/auth/jose/jws.py
mkfst/auth/jose/jwt.py
mkfst/auth/jose/utils.py
mkfst/auth/jose/backends/__init__.py
mkfst/auth/jose/backends/_asn1.py
mkfst/auth/jose/backends/base.py
mkfst/auth/jose/backends/cryptography_backend.py
mkfst/auth/jose/backends/ecdsa_backend.py
mkfst/auth/jose/backends/native.py
mkfst/auth/jose/backends/rsa_backend.py
mkfst/caching/__init__.py
mkfst/caching/base.py
mkfst/caching/decorators.py
mkfst/caching/exceptions.py
mkfst/caching/lock.py
mkfst/caching/plugins.py
mkfst/caching/backends/__init__.py
mkfst/caching/backends/memory.py
mkfst/caching/serializers/__init__.py
mkfst/caching/serializers/serializers.py
mkfst/connection/__init__.py
mkfst/connection/addresses/__init__.py
mkfst/connection/addresses/subnet_range.py
mkfst/connection/base/__init__.py
mkfst/connection/base/connection_type.py
mkfst/connection/tcp/__init__.py
mkfst/connection/tcp/fabricator.py
mkfst/connection/tcp/mercury_sync_http_connection.py
mkfst/connection/tcp/mercury_sync_tcp_connection.py
mkfst/connection/tcp/router.py
mkfst/connection/tcp/protocols/__init__.py
mkfst/connection/tcp/protocols/flow_control.py
mkfst/connection/tcp/protocols/mercury_sync_tcp_client_protocol.py
mkfst/connection/tcp/protocols/mercury_sync_tcp_server_protocol.py
mkfst/connection/tcp/protocols/patterns.py
mkfst/connection/tcp/protocols/receive_buffer.py
mkfst/connection/tcp/protocols/server_state.py
mkfst/connection/tcp/protocols/utils.py
mkfst/connection/tcp/protocols/validate.py
mkfst/docs/__init__.py
mkfst/docs/endpoint_parser.py
mkfst/docs/models.py
mkfst/docs/pages.py
mkfst/docs/parse_examples.py
mkfst/docs/parse_model.py
mkfst/docs/parse_param.py
mkfst-0.5.10.dist-info/licenses/LICENSE
mkfst-0.5.10.dist-info/METADATA
mkfst-0.5.10.dist-info/WHEEL
mkfst-0.5.10.dist-info/top_level.txt
mkfst-0.5.10.dist-info/RECORD
