Metadata-Version: 2.4
Name: mkfst
Version: 0.5.10
Summary: MKFST (Make Fast) is a high-performance, async, non-ASGI, Python HTTP webserver framework
Author-email: Ada Lundhe <adalundhe@lundhe.audio>
License: MIT License
Project-URL: Homepage, https://github.com/hyper-light/mkfst-py
Keywords: pypi,http,rest,framework,web,python,api
Classifier: Programming Language :: Python :: 3.12
Classifier: Programming Language :: Python :: 3.13
Classifier: Programming Language :: Python :: 3.14
Classifier: License :: OSI Approved :: MIT License
Classifier: Operating System :: OS Independent
Requires-Python: >=3.11
License-File: LICENSE
Requires-Dist: psutil
Requires-Dist: uvloop
Requires-Dist: pydantic
Requires-Dist: zstandard
Requires-Dist: cryptography
Requires-Dist: python-dotenv
Requires-Dist: orjson
Requires-Dist: msgspec
Provides-Extra: auth
Requires-Dist: pycryptodome; extra == "auth"
Requires-Dist: rsa; extra == "auth"
Requires-Dist: ecdsa!=0.15; extra == "auth"
Requires-Dist: pyasn1; extra == "auth"
Dynamic: license-file
